setup.py
nivad/__init__.py
nivad/push.py
nivad/push_click_action.py
nivad/push_filters.py
nivad.egg-info/PKG-INFO
nivad.egg-info/SOURCES.txt
nivad.egg-info/dependency_links.txt
nivad.egg-info/not-zip-safe
nivad.egg-info/requires.txt
nivad.egg-info/top_level.txt