Metadata-Version: 1.0
Name: nivad
Version: 0.0.3
Summary: Nivad server-server api package
Home-page: https://github.com/NivadCloud/NivadPy
Author: MJafar Mashhadi
Author-email: mjafar@nivad.io
License: GPL
Platform: UNKNOWN
